serviceinstaller.py
serviceinstaller-0.2.0.dist-info/LICENSE.txt
serviceinstaller-0.2.0.dist-info/METADATA
serviceinstaller-0.2.0.dist-info/WHEEL
serviceinstaller-0.2.0.dist-info/top_level.txt
serviceinstaller-0.2.0.dist-info/RECORD
