Metadata-Version: 2.1
Name: serviceinstaller
Version: 0.2.0
Summary: A flexible service installer, currently compatible with Linux Systemd.
Home-page: https://github.com/cam-gerlach/serviceinstaller
Author: C.A.M. Gerlach
Author-email: CAM.Gerlach@Gerlach.CAM
License: MIT
Project-URL: Repository, https://github.com/cam-gerlach/serviceinstaller
Project-URL: Changelog, https://github.com/cam-gerlach/serviceinstaller/blob/master/CHANGELOG.md
Project-URL: Issue Tracker, https://github.com/cam-gerlach/serviceinstaller/issues
Keywords: systemd service linux unit installer
Classifier: Development Status :: 3 - Alpha
Classifier: Intended Audience :: Developers
Classifier: Intended Audience :: System Administrators
Classifier: License :: OSI Approved :: MIT License
Classifier: Operating System :: POSIX :: Linux
Classifier: Programming Language :: Python :: 3
Classifier: Programming Language :: Python :: 3 :: Only
Classifier: Programming Language :: Python :: 3.6
Classifier: Programming Language :: Python :: 3.7
Classifier: Programming Language :: Python :: 3.8
Classifier: Programming Language :: Python :: 3.9
Classifier: Programming Language :: Python :: 3.10
Classifier: Topic :: System :: Installation/Setup
Classifier: Topic :: System :: Operating System
Classifier: Topic :: System :: Software Distribution
Classifier: Topic :: System :: Systems Administration
Classifier: Topic :: Utilities
Requires-Python: >=3.6
License-File: LICENSE.txt
